Workbook

Sheet Feuille 1 - Ensembles des param
A1: Ensembles des paramètres
A2: Paramètre | B2: Valeur | C2: Unité | D2: Commentaire
A3: Nombre d’affiches | B3: 100 | C3: affiches | D3: Nombre d’affiche à produire
A4: Format | B4: A2
A5: Grammage du papier | B5: 160 | C5: G/m2
A6: Nombre de couleurs | B6: 2 | C6: couleurs | D6: Nombre d’écrans/couleurs à préparer
A7: Matériel sérigraphie à amortir | B7: 180 | C7: € | D7: Kit Serigraphie « Papier A3+ » et cadre A2 Dipilu
A8: Matériel pour faire du papier à amortir | B8: 110 | C8: € | D8: Temps de fabrication + Matière première
A9: Durée d’amortissement du matériel | B9: 1000 | C9: affiches | D9: Hypothèse de durée de vie totale
A10: Taux horaire cible pour le travail | B10: 20 | C10: €/h
A11: Provision cotisations artiste-auteur | B11: 0.1863 | C11: % du bénéfice cible | D11: Approximation indicative pour simulation BNC 2026
A12: Taux de pertes / gâche | B12: 0.15 | C12: %
A13: Prix de l’émulsion | B13: 36.95 | C13: €/unité | D13: Easy Blue 980g
A14: Prix papier transparent | B14: 1 | C14: /A3/couleur
A15: Quantité d’émulsion par couleur/écran | B15: 0.05 | C15: du pot par A2 | D15: 50g pour un pot de 980g
A16: Coût électricité par tirage | B16: 0.5 | C16: €/émulsion | D16: Cuisson de l’encre, séchage, exposition/lumière, etc
A17: Coût eau par tirage | B17: 0.2 | C17: €/émulsion | D17: 60L par emulsión
A18: Coût nettoyant par tirage | B18: 1.5 | C18: émulsion | D18: Nettoyant, savon, produits de nettoyage
A19: Temps preparation T Base | B19: 60 | C19: minutes les 750g
A20: Temps préparation motif | B20: 10 | C20: minutes/tirage | D20: Préparation du fichier pour l’impression
A21: Temps préparation écran / émulsion / exposition par couleur | B21: 40 | C21: minutes/couleur | D21: Préparation, enduction, séchage actif, exposition, dépouillement
A22: Temps calage / repérage par couleur | B22: 15 | C22: minutes/couleur | D22: Installation et essais de repérage
A23: Temps impression par affiche et par couleur | B23: 0.5 | C23: minutes
A24: Temps manipulation/contrôle par affiche | B24: 0.5 | C24: minutes
A25: Temps nettoyage final par couleur | B25: 20 | C25: minutes/couleur | D25: Nettoyage écran/raclette et poste de travail
A26: Temps préparation papier recyclé | B26: 40 | C26: minutes/20 feuilles | D26: Pas de matière première payante
A27: Temps de récolte/tri du papier pour la pâte à papier | B27: 0.5 | C27: h/kg
A28: Charges globales mensuelles | B28: 350 | C28: €/mois | D28: Loyer dans le Vexin et logiciels opensources gratuit
A29: Nombre d’heures travaillé par jour | B29: 8 | C29: heures
A30: Achat massicot | B30: 190 | C30: € | D30: Dahl 444 920mm
A31: Temps découpe Massicot | B31: 0.5 | C31: Min/coupe

Sheet Feuille 1 - Production du papie
A1: Production du papier
B2: Valeur | C2: Unité | D2: Commentaire
A3: Format de l’affiche | B3: {='Feuille 1 - Ensembles des param'!B4} -> A2 | C3: format
A4: Surface de l’affiche | B4: {=INDEX($D$27:$D$30,MATCH($B$3,$A$27:$A$30,0))} -> 0.24948 | C4: m²
A5: Facteur de surface par rapport au A2 | B5: {=INDEX($E$27:$E$30,MATCH($B$3,$A$27:$A$30,0))} -> 1 | D5: Multiplie émulsion, T-base, pigments (calculés pour du A2).
A6: Nombre de feuilles A2 à produire | B6: {=ROUNDUP('Feuille 1 - Ensembles des param'!B3+('Feuille 1 - Ensembles des param'!B3*'Feuille 1 - Ensembles des param'!B12),0)} -> 115
A7: Film transparent en équivalent A3 | B7: {=B4/$D$28} -> 2 | C7: A3 par couleur
A8: Affiches par feuille fabriquée | B8: {=INDEX($F$27:$F$30,MATCH($B$3,$A$27:$A$30,0))} -> 1 | C8: affiches | D8: Le massicot augmente le nombre d’affiches par feuille A2.
A9: Affiches à imprimer (pertes comprises) | B9: {=ROUNDUP('Feuille 1 - Ensembles des param'!B3+'Feuille 1 - Ensembles des param'!B3*'Feuille 1 - Ensembles des param'!B12,0)} -> 115 | C9: affiches | D9: Même taux de pertes que le reste du tableau.
A10: Feuilles à fabriquer | B10: {=ROUNDUP(B9/B8,0)} -> 115 | C10: feuilles | D10: Feuilles A2 si découpe, sinon feuilles au format de l’affiche.
A11: Surface d’une feuille fabriquée | B11: {=$D$27} -> 0.24948 | C11: m²
A12: Équivalent A2 à imprimer | B12: {=B9*B5} -> 115 | C12: feuilles A2 | D12: Base de calcul de l’émulsion, de la T-base et des pigments.
A13: Nombre de coupes au massicot | B13: {=B6*INDEX($G$27:$G$30,MATCH($B$3,$A$27:$A$30,0))} -> 460 | C13: coupes
A14: Temps de découpe | B14: {='Feuille 1 - Ensembles des param'!B31*B13} -> 230 | C14: minutes
A15: Amortissement massicot | B15: {='Feuille 1 - Ensembles des param'!B3/'Feuille 1 - Ensembles des param'!B9*'Feuille 1 - Ensembles des param'!B30} -> 19 | C15: €
A16: Poids d’une feuille fabriquée | B16: {=B11*'Feuille 1 - Ensembles des param'!B5} -> 39.9168 | C16: g
A17: Fibres à collecter | B17: {=B16/1000*B10} -> 4.590432 | C17: kg
A18: Temps de récolte/tri du papier | B18: {=B17*'Feuille 1 - Ensembles des param'!B27*60} -> 137.71296 | C18: minutes
A19: Temps production | B19: {=B10*'Feuille 1 - Ensembles des param'!B26/20+B14} -> 460 | C19: minutes
A20: Temps total de production | B20: {=B18+B19} -> 597.71296 | C20: Minutes
A21: Prix total | B21: {=B15+B20/60*'Feuille 1 - Ensembles des param'!B10} -> 218.23765
A22: Prix par feuilles | B22: {=B21/'Feuille 1 - Ensembles des param'!B3} -> 2.1823765
A23: Pourcentage dans le prix final | B23: {=('Feuille 1 - Tableau 1-1-1-1-1'!B1-B21)/'Feuille 1 - Tableau 1-1-1-1-1'!B1} -> 0.5280799
A25: Formats disponibles
A26: Format | B26: Largeur (mm) | C26: Hauteur (mm) | D26: Surface (m²) | E26: Facteur | F26: Affiches par feuille A2 | G26: Coupes par feuille A2
A27: A2 | B27: 420 | C27: 594 | D27: {=B27*C27/1000000} -> 0.24948 | E27: {=D27/$D$27} -> 1 | F27: {=ROUND($D$27/D27,0)} -> 1 | G27: {=F27+3} -> 4
A28: A3 | B28: 297 | C28: 420 | D28: {=B28*C28/1000000} -> 0.12474 | E28: {=D28/$D$27} -> 0.5 | F28: {=ROUND($D$27/D28,0)} -> 2 | G28: {=F28+3} -> 5
A29: A4 | B29: 210 | C29: 297 | D29: {=B29*C29/1000000} -> 0.06237 | E29: {=D29/$D$27} -> 0.25 | F29: {=ROUND($D$27/D29,0)} -> 4 | G29: {=F29+3} -> 7
A30: A5 | B30: 148 | C30: 210 | D30: {=B30*C30/1000000} -> 0.03108 | E30: {=D30/$D$27} -> 0.12457912 | F30: {=ROUND($D$27/D30,0)} -> 8 | G30: {=F30+3} -> 11

Sheet Feuille 1 - Production de la T 
A1: Production de la T Base de Serigraphie
A2: Resources | B2: Prix | C2: Quantité en L et Kg | E2: Prix au Litre/kg | F2: Quantité nécessaire en mL et g | H2: Prix recette
A3: Eau | B3: 0.0049 | C3: 1 | D3: L | E3: {=$B3/$C3} -> 0.0049 | F3: 530 | G3: mL | H3: {=$E3*($F3/1000)} -> 0.002597
A4: Vinaigre de pomme | B4: 8 | C4: 0.75 | D4: L | E4: {=$B4/$C4} -> 10.666667 | F4: 120 | G4: mL | H4: {=$E4*($F4/1000)} -> 1.28
A5: Farine de blé | B5: 20 | C5: 10 | D5: kg | E5: {=$B5/$C5} -> 2 | F5: 80 | G5: g | H5: {=$E5*($F5/1000)} -> 0.16
A6: Fécule de Maïs | B6: 2 | C6: 0.7 | D6: kg | E6: {=$B6/$C6} -> 2.8571429 | F6: 16 | G6: g | H6: {=$E6*($F6/1000)} -> 0.045714286
A7: Sucre | B7: 1.85 | C7: 1 | D7: kg | E7: {=$B7/$C7} -> 1.85 | F7: 12 | G7: g | H7: {=$E7*($F7/1000)} -> 0.0222
A8: Miel | B8: 13 | C8: 1 | D8: kg | E8: {=$B8/$C8} -> 13 | F8: 5 | G8: g | H8: {=$E8*($F8/1000)} -> 0.065
A10: Total ressources pour 100 feuilles A2 | E10: {=E3+E4+E5+E6+E7+E8} -> 30.37871 | H10: {=H3+H4+H5+H6+H7+H8} -> 1.5755113
A11: Total avec temps de travail pour 100 feuilles A2 | E11: {=E10+'Feuille 1 - Ensembles des param'!B19} -> 90.37871 | H11: {=H10+'Feuille 1 - Ensembles des param'!B19/60*'Feuille 1 - Ensembles des param'!B10} -> 21.575511
A12: Total pour le projet | H12: {=H11/100*'Feuille 1 - Production du papie'!B12} -> 24.811838

Sheet Feuille 1 - Production des pigm
A1: Production des pigments
A2: Pigment | B2: Temps de preparation en min | C2: Unité | D2: Commentaire
A3: Broux de noix | B3: 150 | C3: minutes
A4: Charbon | B4: 60 | C4: minutes
A5: Craie blanche | B5: 120 | C5: minutes
A6: Mures | B6: 60 | C6: minutes
A7: Pastel | B7: 200 | C7: minutes | D7: Beaucoup plus de temps avec le séchage et la fermentation
A8: Moyenne | B8: {=AVERAGE(B3,B4,B5,B6,B7)} -> 118 | C8: minutes
A10: Prix | B10: {=B8/60*'Feuille 1 - Ensembles des param'!B10} -> 39.333333 | C10: € | D10: Ce prix pour une grande quantité de pigment dont la quantité dans le produit fini est inférieur
A11: Prix pour le projet | B11: {=B10*'Feuille 1 - Ensembles des param'!B6*'Feuille 1 - Production du papie'!B12/1000} -> 9.0466667 | C11: € | D11: 10% de la quantité de pigment par couleur pour 100 feuilles

Sheet Feuille 1 - Serigraphie
A1: Serigraphie
B2: Valeur | C2: Unité | D2: Commentaire
A3: Amortissement matériel | B3: {='Feuille 1 - Ensembles des param'!B7/'Feuille 1 - Ensembles des param'!B9*'Feuille 1 - Ensembles des param'!B3} -> 18 | C3: €
A4: Prix des consommables par couleur | B4: {='Feuille 1 - Ensembles des param'!B13*'Feuille 1 - Ensembles des param'!B15*(1/'Feuille 1 - Production du papie'!B5)+'Feuille 1 - Ensembles des param'!B14+'Feuille 1 - Ensembles des param'!B16+'Feuille 1 - Ensembles des param'!B17+'Feuille 1 - Ensembles des param'!B18+'Feuille 1 - Production de la T '!H10+'Feuille 1 - Production du papie'!B7*'Feuille 1 - Ensembles des param'!B14} -> 8.6230113 | C4: €
A5: Temps par couleur | B5: {=ROUND('Feuille 1 - Ensembles des param'!B19+'Feuille 1 - Ensembles des param'!B20+'Feuille 1 - Ensembles des param'!B21+'Feuille 1 - Ensembles des param'!B22+'Feuille 1 - Ensembles des param'!B23*'Feuille 1 - Production du papie'!B6+'Feuille 1 - Ensembles des param'!B24+'Feuille 1 - Ensembles des param'!B25,1)} -> 203 | C5: minutes
A6: Prix des consommables pour le projet | B6: {=B4*'Feuille 1 - Ensembles des param'!B6} -> 17.246023 | C6: €
A7: Temps pour le projet | B7: {=B5*'Feuille 1 - Ensembles des param'!B6} -> 406 | C7: minutes
A8: Prix de la serigraphie | B8: {=B3+B6+B7/60*'Feuille 1 - Ensembles des param'!B10} -> 170.57936 | C8: €

Sheet Feuille 1 - Temps de travail et
A1: Temps de travail et charges immuables
B2: Valeur | C2: Unité | D2: Commentaire
A3: Temps total travaillé | B3: {='Feuille 1 - Serigraphie'!B7+'Feuille 1 - Production du papie'!B20+'Feuille 1 - Production des pigm'!B8*'Feuille 1 - Ensembles des param'!B6/1000*'Feuille 1 - Production du papie'!B12+'Feuille 1 - Ensembles des param'!B19/100*'Feuille 1 - Ensembles des param'!B3} -> 1090.853 | C3: minutes
A4: Nombre d’heures travaillé | B4: {=B3/60} -> 18.180883 | C4: heures
A5: Nombres de jour de travail | B5: {=B4/'Feuille 1 - Ensembles des param'!B29} -> 2.2726103 | C5: jours
A6: Montant des charges | B6: {='Feuille 1 - Ensembles des param'!B28/20*B5} -> 39.770681 | C6: € | D6: Charges reparti sur 20j/mois

Sheet Feuille 1 - Tableau 1-1-1-1-1
A1: Montant avant impôt total | B1: {='Feuille 1 - Production des pigm'!B11+'Feuille 1 - Production du papie'!B21+'Feuille 1 - Serigraphie'!B8+'Feuille 1 - Production de la T '!H12+'Feuille 1 - Temps de travail et'!B6} -> 462.44619
A2: Montant de la valeur du travail | B2: {='Feuille 1 - Temps de travail et'!B4*'Feuille 1 - Ensembles des param'!B10} -> 363.61765
A3: Part de la valeur travail dans le montant | B3: {=B2/B1} -> 0.78629181
A4: Montant HT (pas de TVA en dessous de 50’000€/an) | B4: {=B1+B1*'Feuille 1 - Ensembles des param'!B11} -> 548.59992
A5: Montant HT par affiche | B5: {=B4/'Feuille 1 - Ensembles des param'!B3} -> 5.4859992
